helloworld.py
helloworld_zain-0.0.1.dist-info/METADATA
helloworld_zain-0.0.1.dist-info/WHEEL
helloworld_zain-0.0.1.dist-info/top_level.txt
helloworld_zain-0.0.1.dist-info/RECORD
