Metadata-Version: 2.1
Name: helloworld-zain
Version: 0.0.1
Summary: Say Hello by Zain!
Home-page: UNKNOWN
Author: UNKNOWN
Author-email: UNKNOWN
License: UNKNOWN
Platform: UNKNOWN
